{"data":[{"id":1,"id_padre":1,"label":"Preescolar","activo":1,"detalles":[]},{"id":2,"id_padre":1,"label":"Primaria","activo":1,"detalles":[]},{"id":3,"id_padre":1,"label":"Secundaria","activo":1,"detalles":[]},{"id":4,"id_padre":1,"label":"Bachillerato","activo":1,"detalles":[]},{"id":5,"id_padre":2,"label":"1º","activo":1,"detalles":[]},{"id":6,"id_padre":2,"label":"2º","activo":1,"detalles":[]},{"id":7,"id_padre":2,"label":"3º","activo":1,"detalles":[]},{"id":8,"id_padre":2,"label":"4º","activo":1,"detalles":[]},{"id":9,"id_padre":2,"label":"5º","activo":1,"detalles":[]},{"id":10,"id_padre":2,"label":"6º","activo":1,"detalles":[]},{"id":11,"id_padre":3,"label":"Lenguajes","activo":1,"detalles":[],"svg":{"clasehtml":"","datasvg":{"changingThisBreaksApplicationSecurity":"<svg class=\"d_navlenguajes\" viewBox=\"0 0 200 200\">\n                            <path d=\"M107.7,144.6c-5.6-1.9-11.8,0.9-13.9,6.5c-2.2,5.7,0.7,12.1,6.5,14.3c3,1.1,6.3,0.9,9.1-0.6\n                                c1.5-0.8,3.3-0.2,4.1,1.3c0.8,1.5,0.2,3.3-1.3,4.1c-2.5,1.3-5.3,2-8,2c-2.1,0-4.1-0.4-6.1-1.1c-7.5-2.9-11.8-10.4-10.9-18.1\n                                c-2.8,1.1-5.8,1.7-8.8,1.7c-3,0-6-0.5-8.8-1.6c-2.4-0.9-4.5-2.1-6.5-3.6c0.7,1.9,1.4,3.9,2.3,5.8c6.8,15.1,18.3,26.6,28.7,28.7\n                                c0,0,0,0,0,0c1.3,0.3,4.8,0.9,7.2,0.5c0.1,0,0.7-0.1,0.7-0.1c7.9-0.8,14.6-5.9,17.4-13.3c2-5.2,1.8-10.8-0.5-15.9\n                                C116.8,150.4,112.8,146.6,107.7,144.6\" />\n                            <path d=\"M50.9,96.1c-2.8-1-5.8-1-8.5,0.3c-2.7,1.2-4.8,3.4-5.8,6.2c-1.1,3-0.9,6.3,0.6,9.1c0.8,1.5,0.2,3.3-1.3,4.1\n                                c-0.4,0.3-0.9,0.4-1.4,0.4c-1.1,0-2.2-0.6-2.7-1.6c-2.3-4.4-2.6-9.5-0.9-14.1c1.6-4.3,4.8-7.7,9-9.6c2.9-1.3,6-1.7,9-1.4\n                                c-2.1-5.6-2.2-11.8,0-17.6c0.9-2.4,2.1-4.5,3.6-6.5c-1.9,0.7-3.9,1.4-5.8,2.3C31.6,74.5,20,86.1,18,96.4c0,0,0,0,0,0\n                                c-0.3,1.3-0.9,4.8-0.5,7.2c0,0.1,0.1,0.7,0.1,0.8c0.8,7.9,5.9,14.5,13.3,17.4c5.2,2,10.8,1.8,15.9-0.5c4.9-2.2,8.7-6.2,10.7-11.3\n                                C59.3,104.4,56.4,98.2,50.9,96.1\" />\n                            <path\n                                d=\"M98,131.3c16.5,0,30-13.4,30-30c0-16.5-13.4-30-30-30c-16.5,0-30,13.4-30,30C68.1,117.9,81.5,131.3,98,131.3\" />\n                            <path\n                                d=\"M129.6,56.5c-1.9-16.4-9.4-31-18.6-36.1c-1.1-0.7-4.4-2.3-6.7-2.7c-0.1,0-0.7-0.2-0.8-0.2\n                                c-7.7-1.7-15.6,1.2-20.6,7.4c-7.1,8.9-5.6,21.7,3.1,28.9c2.3,1.7,5,2.5,7.9,2.2c2.9-0.3,5.6-1.8,7.4-4.1c1.8-2.3,2.7-5.2,2.3-8.1\n                                c-0.3-2.9-1.8-5.6-4.1-7.4c-2.5-2-5.7-2.8-8.9-2.2c-1.7,0.3-3.2-0.8-3.5-2.5c-0.3-1.7,0.8-3.2,2.4-3.5c4.9-0.9,9.9,0.4,13.7,3.4\n                                c3.6,2.9,5.9,6.9,6.4,11.5c0.4,3.1-0.2,6.2-1.5,9c5.9-0.3,11.9,1.5,16.8,5.4c2,1.6,3.7,3.4,5,5.4C130,60.7,129.9,58.6,129.6,56.5\" />\n                            <path d=\"M183.5,99c-0.8-7.8-5.9-14.5-13.3-17.3c-10.6-4-22.4,1.3-26.6,11.7c-1.9,5.6,0.9,11.8,6.5,14\n                                c2.8,1.1,5.8,1,8.5-0.3c2.7-1.2,4.8-3.4,5.8-6.2c1.1-3,0.9-6.3-0.6-9.1c-0.8-1.5-0.2-3.3,1.3-4.1c1.5-0.8,3.3-0.2,4.1,1.2\n                                c2.3,4.4,2.6,9.5,0.9,14.1c-1.6,4.3-4.8,7.7-9,9.6c-2.3,1-4.6,1.5-7,1.5c-0.7,0-1.3-0.1-2-0.2c2.1,5.6,2.2,11.8,0,17.6\n                                c-0.9,2.4-2.1,4.5-3.6,6.5c1.9-0.7,3.9-1.4,5.8-2.3c15.1-6.8,26.6-18.3,28.7-28.6c0.3-1.2,0.9-4.9,0.6-7.3\n                                C183.6,99.7,183.5,99.1,183.5,99\" />\n                        </svg>"},"datasvghtml":{"changingThisBreaksApplicationSecurity":"<svg class=\"d_navlenguajes\" viewBox=\"0 0 200 200\">\n                            <path d=\"M107.7,144.6c-5.6-1.9-11.8,0.9-13.9,6.5c-2.2,5.7,0.7,12.1,6.5,14.3c3,1.1,6.3,0.9,9.1-0.6\n                                c1.5-0.8,3.3-0.2,4.1,1.3c0.8,1.5,0.2,3.3-1.3,4.1c-2.5,1.3-5.3,2-8,2c-2.1,0-4.1-0.4-6.1-1.1c-7.5-2.9-11.8-10.4-10.9-18.1\n                                c-2.8,1.1-5.8,1.7-8.8,1.7c-3,0-6-0.5-8.8-1.6c-2.4-0.9-4.5-2.1-6.5-3.6c0.7,1.9,1.4,3.9,2.3,5.8c6.8,15.1,18.3,26.6,28.7,28.7\n                                c0,0,0,0,0,0c1.3,0.3,4.8,0.9,7.2,0.5c0.1,0,0.7-0.1,0.7-0.1c7.9-0.8,14.6-5.9,17.4-13.3c2-5.2,1.8-10.8-0.5-15.9\n                                C116.8,150.4,112.8,146.6,107.7,144.6\" />\n                            <path d=\"M50.9,96.1c-2.8-1-5.8-1-8.5,0.3c-2.7,1.2-4.8,3.4-5.8,6.2c-1.1,3-0.9,6.3,0.6,9.1c0.8,1.5,0.2,3.3-1.3,4.1\n                                c-0.4,0.3-0.9,0.4-1.4,0.4c-1.1,0-2.2-0.6-2.7-1.6c-2.3-4.4-2.6-9.5-0.9-14.1c1.6-4.3,4.8-7.7,9-9.6c2.9-1.3,6-1.7,9-1.4\n                                c-2.1-5.6-2.2-11.8,0-17.6c0.9-2.4,2.1-4.5,3.6-6.5c-1.9,0.7-3.9,1.4-5.8,2.3C31.6,74.5,20,86.1,18,96.4c0,0,0,0,0,0\n                                c-0.3,1.3-0.9,4.8-0.5,7.2c0,0.1,0.1,0.7,0.1,0.8c0.8,7.9,5.9,14.5,13.3,17.4c5.2,2,10.8,1.8,15.9-0.5c4.9-2.2,8.7-6.2,10.7-11.3\n                                C59.3,104.4,56.4,98.2,50.9,96.1\" />\n                            <path\n                                d=\"M98,131.3c16.5,0,30-13.4,30-30c0-16.5-13.4-30-30-30c-16.5,0-30,13.4-30,30C68.1,117.9,81.5,131.3,98,131.3\" />\n                            <path\n                                d=\"M129.6,56.5c-1.9-16.4-9.4-31-18.6-36.1c-1.1-0.7-4.4-2.3-6.7-2.7c-0.1,0-0.7-0.2-0.8-0.2\n                                c-7.7-1.7-15.6,1.2-20.6,7.4c-7.1,8.9-5.6,21.7,3.1,28.9c2.3,1.7,5,2.5,7.9,2.2c2.9-0.3,5.6-1.8,7.4-4.1c1.8-2.3,2.7-5.2,2.3-8.1\n                                c-0.3-2.9-1.8-5.6-4.1-7.4c-2.5-2-5.7-2.8-8.9-2.2c-1.7,0.3-3.2-0.8-3.5-2.5c-0.3-1.7,0.8-3.2,2.4-3.5c4.9-0.9,9.9,0.4,13.7,3.4\n                                c3.6,2.9,5.9,6.9,6.4,11.5c0.4,3.1-0.2,6.2-1.5,9c5.9-0.3,11.9,1.5,16.8,5.4c2,1.6,3.7,3.4,5,5.4C130,60.7,129.9,58.6,129.6,56.5\" />\n                            <path d=\"M183.5,99c-0.8-7.8-5.9-14.5-13.3-17.3c-10.6-4-22.4,1.3-26.6,11.7c-1.9,5.6,0.9,11.8,6.5,14\n                                c2.8,1.1,5.8,1,8.5-0.3c2.7-1.2,4.8-3.4,5.8-6.2c1.1-3,0.9-6.3-0.6-9.1c-0.8-1.5-0.2-3.3,1.3-4.1c1.5-0.8,3.3-0.2,4.1,1.2\n                                c2.3,4.4,2.6,9.5,0.9,14.1c-1.6,4.3-4.8,7.7-9,9.6c-2.3,1-4.6,1.5-7,1.5c-0.7,0-1.3-0.1-2-0.2c2.1,5.6,2.2,11.8,0,17.6\n                                c-0.9,2.4-2.1,4.5-3.6,6.5c1.9-0.7,3.9-1.4,5.8-2.3c15.1-6.8,26.6-18.3,28.7-28.6c0.3-1.2,0.9-4.9,0.6-7.3\n                                C183.6,99.7,183.5,99.1,183.5,99\" />\n                        </svg>\n                                            <span>Lenguajes</span>"}}},{"id":12,"id_padre":3,"label":"Saberes y pensamiento científico","activo":1,"detalles":[],"svg":{"clasehtml":"","datasvg":{"changingThisBreaksApplicationSecurity":"<svg class=\"d_navsaberes\" viewBox=\"0 0 200 200\">\n                                <path d=\"M139.3,53.3c3.6-6.9,5.7-14.8,5.7-23.3h-12.6c0,18.7-14.1,33.8-31.6,33.8S69.2,48.7,69.2,30H56.6\n                                    c0,25.8,19.3,46.8,43.3,47.3c-3.6,6.8-5.7,14.8-5.7,23.2h0c0,18.7-14.1,33.8-31.6,33.8S31,119.2,31,100.5H18.4\n                                    c0,26.1,19.8,47.3,44.2,47.3c0.3,0,0.6,0,0.9,0c-3.5,6.8-5.6,14.6-5.6,23h12.6c0-18.7,14.1-33.8,31.6-33.8s31.6,15.2,31.6,33.8\n                                    h12.6c0-26.1-19.8-47.3-44.2-47.3c-0.3,0-0.6,0-0.9,0c3.5-6.8,5.5-14.6,5.6-22.9h0c0-18.7,14.1-33.8,31.6-33.8S170,81.9,170,100.6\n                                    h12.6C182.6,74.8,163.2,53.8,139.3,53.3z\"/>\n                                <rect x=\"170.3\" y=\"105.4\" width=\"12\" height=\"12.9\"/>\n                                <rect x=\"18.9\" y=\"84.1\" width=\"12\" height=\"12.9\"/>\n                                <path d=\"M140.2,90.6c6.6,0,11.9,5.7,11.9,12.8c0,7.1-5.3,12.8-11.9,12.8c-6.6,0-11.9-5.7-11.9-12.8\n                                    C128.3,96.3,133.6,90.6,140.2,90.6\"/>\n                                <path d=\"M62.6,88.6c6.6,0,11.9,5.7,11.9,12.8c0,7.1-5.3,12.8-11.9,12.8c-6.6,0-11.9-5.7-11.9-12.8\n                                    C50.7,94.3,56,88.6,62.6,88.6\"/>\n                                <path d=\"M100.8,18.5c6.6,0,11.9,5.7,11.9,12.8c0,7.1-5.3,12.8-11.9,12.8c-6.6,0-11.9-5.7-11.9-12.8\n                                    C88.9,24.2,94.2,18.5,100.8,18.5\"/>\n                                <path d=\"M102.1,157c6.6,0,11.9,5.7,11.9,12.8c0,7.1-5.3,12.8-11.9,12.8c-6.6,0-11.9-5.7-11.9-12.8\n                                    C90.2,162.7,95.5,157,102.1,157\"/>\n                            </svg>"},"datasvghtml":{"changingThisBreaksApplicationSecurity":"<svg class=\"d_navsaberes\" viewBox=\"0 0 200 200\">\n                                <path d=\"M139.3,53.3c3.6-6.9,5.7-14.8,5.7-23.3h-12.6c0,18.7-14.1,33.8-31.6,33.8S69.2,48.7,69.2,30H56.6\n                                    c0,25.8,19.3,46.8,43.3,47.3c-3.6,6.8-5.7,14.8-5.7,23.2h0c0,18.7-14.1,33.8-31.6,33.8S31,119.2,31,100.5H18.4\n                                    c0,26.1,19.8,47.3,44.2,47.3c0.3,0,0.6,0,0.9,0c-3.5,6.8-5.6,14.6-5.6,23h12.6c0-18.7,14.1-33.8,31.6-33.8s31.6,15.2,31.6,33.8\n                                    h12.6c0-26.1-19.8-47.3-44.2-47.3c-0.3,0-0.6,0-0.9,0c3.5-6.8,5.5-14.6,5.6-22.9h0c0-18.7,14.1-33.8,31.6-33.8S170,81.9,170,100.6\n                                    h12.6C182.6,74.8,163.2,53.8,139.3,53.3z\"/>\n                                <rect x=\"170.3\" y=\"105.4\" width=\"12\" height=\"12.9\"/>\n                                <rect x=\"18.9\" y=\"84.1\" width=\"12\" height=\"12.9\"/>\n                                <path d=\"M140.2,90.6c6.6,0,11.9,5.7,11.9,12.8c0,7.1-5.3,12.8-11.9,12.8c-6.6,0-11.9-5.7-11.9-12.8\n                                    C128.3,96.3,133.6,90.6,140.2,90.6\"/>\n                                <path d=\"M62.6,88.6c6.6,0,11.9,5.7,11.9,12.8c0,7.1-5.3,12.8-11.9,12.8c-6.6,0-11.9-5.7-11.9-12.8\n                                    C50.7,94.3,56,88.6,62.6,88.6\"/>\n                                <path d=\"M100.8,18.5c6.6,0,11.9,5.7,11.9,12.8c0,7.1-5.3,12.8-11.9,12.8c-6.6,0-11.9-5.7-11.9-12.8\n                                    C88.9,24.2,94.2,18.5,100.8,18.5\"/>\n                                <path d=\"M102.1,157c6.6,0,11.9,5.7,11.9,12.8c0,7.1-5.3,12.8-11.9,12.8c-6.6,0-11.9-5.7-11.9-12.8\n                                    C90.2,162.7,95.5,157,102.1,157\"/>\n                            </svg>\n                                            <span>Saberes y pensamiento científico</span>\n                                            "}}},{"id":13,"id_padre":3,"label":"Ética, naturaleza y sociedades","activo":1,"detalles":[],"svg":{"clasehtml":"","datasvg":{"changingThisBreaksApplicationSecurity":"<svg class=\"d_navetica\" viewBox=\"0 0 200 200\">\n                                <rect x=\"18.7\" y=\"169.3\" width=\"11.5\" height=\"12.7\"/>\n                                <rect x=\"170.8\" y=\"169.3\" width=\"11.5\" height=\"12.7\"/>\n                                <path d=\"M100.5,18.6c8.9,0,16.1,7.9,16.1,17.6s-7.2,17.6-16.1,17.6c-8.9,0-16.1-7.9-16.1-17.6S91.6,18.6,100.5,18.6\"/>\n                                <path d=\"M114,123.7c28.6-6.5,50.1-34.3,50.2-67.5h0V43.7c-34.5,0.2-62.5,30.8-62.9,68.6c-0.1,0-0.2,0-0.3,0\n                                    c-0.1,0-0.3,0-0.4,0c-0.2-38-28.2-68.7-62.9-68.9v12.9c0,0,0.1,0,0.1,0c0.2,33.2,21.6,60.8,50,67.4c-4.6,25.8-25.3,45.3-50.2,45.5\n                                    v12.9c30.9-0.2,56.5-24.7,61.8-56.9c0.5,0,1,0,1.5,0c0.4,0,0.9,0,1.3,0c5.2,32.4,30.9,57,61.9,57.2v-12.9\n                                    C139.3,169.3,118.6,149.7,114,123.7z M49.7,57.9c22,5.9,38.4,27.2,39.2,52.8C66.9,104.9,50.5,83.6,49.7,57.9z M152.5,58.2\n                                    c-0.9,25.6-17.4,46.8-39.3,52.6C114.1,85.2,130.5,63.9,152.5,58.2z\"/>\n                            </svg>"},"datasvghtml":{"changingThisBreaksApplicationSecurity":"<svg class=\"d_navetica\" viewBox=\"0 0 200 200\">\n                                <rect x=\"18.7\" y=\"169.3\" width=\"11.5\" height=\"12.7\"/>\n                                <rect x=\"170.8\" y=\"169.3\" width=\"11.5\" height=\"12.7\"/>\n                                <path d=\"M100.5,18.6c8.9,0,16.1,7.9,16.1,17.6s-7.2,17.6-16.1,17.6c-8.9,0-16.1-7.9-16.1-17.6S91.6,18.6,100.5,18.6\"/>\n                                <path d=\"M114,123.7c28.6-6.5,50.1-34.3,50.2-67.5h0V43.7c-34.5,0.2-62.5,30.8-62.9,68.6c-0.1,0-0.2,0-0.3,0\n                                    c-0.1,0-0.3,0-0.4,0c-0.2-38-28.2-68.7-62.9-68.9v12.9c0,0,0.1,0,0.1,0c0.2,33.2,21.6,60.8,50,67.4c-4.6,25.8-25.3,45.3-50.2,45.5\n                                    v12.9c30.9-0.2,56.5-24.7,61.8-56.9c0.5,0,1,0,1.5,0c0.4,0,0.9,0,1.3,0c5.2,32.4,30.9,57,61.9,57.2v-12.9\n                                    C139.3,169.3,118.6,149.7,114,123.7z M49.7,57.9c22,5.9,38.4,27.2,39.2,52.8C66.9,104.9,50.5,83.6,49.7,57.9z M152.5,58.2\n                                    c-0.9,25.6-17.4,46.8-39.3,52.6C114.1,85.2,130.5,63.9,152.5,58.2z\"/>\n                            </svg>\n                                            <span>Ética, naturaleza y sociedades</span>"}}},{"id":14,"id_padre":3,"label":"De lo humano y comunitario","activo":1,"detalles":[],"svg":{"clasehtml":"d_ejeartes","datasvg":{"changingThisBreaksApplicationSecurity":"<svg class=\"d_navdelohumano\" viewBox=\"0 0 200 200\">\n                                <path class=\"st0\" d=\"M157,18.5h-16.1c0,22.3-18.1,40.3-40.4,40.3c-22.3,0-40.4-18-40.4-40.3H44.1c0,31.1,25.3,56.4,56.4,56.4\n                                    C131.7,74.9,157,49.6,157,18.5\"/>\n                                <path class=\"st1\" d=\"M40.7,182.5H58c0-24,19.5-43.4,43.5-43.4s43.5,19.4,43.5,43.4h17.3c0-33.5-27.2-60.7-60.8-60.7\n                                    C67.9,121.8,40.7,149,40.7,182.5\"/>\n                                <path class=\"st2\" d=\"M106.9,98.3c0-24.7-20-44.7-44.7-44.7c-21.3,0-39.1,14.9-43.6,34.7h13.2c4.2-12.8,16.2-22,30.4-22\n                                    c17.7,0,32,14.3,32,31.9H106.9z\"/>\n                                <path class=\"st3\" d=\"M169.2,107.9c-4.3,12.6-16.2,21.7-30.3,21.7c-17.7,0-32-14.3-32-31.9H94.2c0,24.7,20,44.7,44.7,44.7\n                                    c21.2,0,38.9-14.7,43.5-34.4H169.2z\"/>\n                                <path class=\"st4\" d=\"M106.9,98.3H94.2c0,17.6-14.3,31.9-32,31.9c-14.3,0-26.5-9.4-30.5-22.4H18.5c4.4,20.1,22.3,35.1,43.7,35.1\n                                    C86.9,143,106.9,123,106.9,98.3\"/>\n                                <path class=\"st5\" d=\"M182.5,88.4c-4.5-19.9-22.3-34.7-43.6-34.7c-24.7,0-44.7,20-44.7,44.7h12.7c0-17.6,14.3-31.9,32-31.9\n                                    c14.2,0,26.2,9.2,30.4,22H182.5z\"/>\n                            </svg>"},"datasvghtml":{"changingThisBreaksApplicationSecurity":"<svg class=\"d_navdelohumano\" viewBox=\"0 0 200 200\">\n                                <path class=\"st0\" d=\"M157,18.5h-16.1c0,22.3-18.1,40.3-40.4,40.3c-22.3,0-40.4-18-40.4-40.3H44.1c0,31.1,25.3,56.4,56.4,56.4\n                                    C131.7,74.9,157,49.6,157,18.5\"/>\n                                <path class=\"st1\" d=\"M40.7,182.5H58c0-24,19.5-43.4,43.5-43.4s43.5,19.4,43.5,43.4h17.3c0-33.5-27.2-60.7-60.8-60.7\n                                    C67.9,121.8,40.7,149,40.7,182.5\"/>\n                                <path class=\"st2\" d=\"M106.9,98.3c0-24.7-20-44.7-44.7-44.7c-21.3,0-39.1,14.9-43.6,34.7h13.2c4.2-12.8,16.2-22,30.4-22\n                                    c17.7,0,32,14.3,32,31.9H106.9z\"/>\n                                <path class=\"st3\" d=\"M169.2,107.9c-4.3,12.6-16.2,21.7-30.3,21.7c-17.7,0-32-14.3-32-31.9H94.2c0,24.7,20,44.7,44.7,44.7\n                                    c21.2,0,38.9-14.7,43.5-34.4H169.2z\"/>\n                                <path class=\"st4\" d=\"M106.9,98.3H94.2c0,17.6-14.3,31.9-32,31.9c-14.3,0-26.5-9.4-30.5-22.4H18.5c4.4,20.1,22.3,35.1,43.7,35.1\n                                    C86.9,143,106.9,123,106.9,98.3\"/>\n                                <path class=\"st5\" d=\"M182.5,88.4c-4.5-19.9-22.3-34.7-43.6-34.7c-24.7,0-44.7,20-44.7,44.7h12.7c0-17.6,14.3-31.9,32-31.9\n                                    c14.2,0,26.2,9.2,30.4,22H182.5z\"/>\n                            </svg>\n                                            <span>De lo humano y comunitario</span>"}}},{"id":15,"id_padre":4,"label":"1","activo":1,"detalles":[]},{"id":16,"id_padre":4,"label":"2","activo":1,"detalles":[]},{"id":17,"id_padre":4,"label":"3","activo":1,"detalles":[]},{"id":18,"id_padre":4,"label":"4","activo":1,"detalles":[]},{"id":19,"id_padre":4,"label":"5","activo":1,"detalles":[]},{"id":20,"id_padre":4,"label":"6","activo":1,"detalles":[]},{"id":21,"id_padre":8,"label":"Inclusión","activo":1,"detalles":[{"id":1489,"id_padre":21,"data":{"svg":"<svg viewBox='0 0 200 200'>                    <path d='M100.5,134.9h24.3c5.6,0,10.1-4.5,10.1-10c0-5.5-4.5-10-10.1-10h-24.3c-2.1,0-3.8-1.7-3.8-3.8v-6.9h-3.1v20.5                            c0,9.7-7.9,17.6-17.5,17.6c-9.7,0-17.5-7.9-17.5-17.6v-20.5h-40c0.7,3,2.2,5.8,4.4,8l65.8,65.8c2.2,2.2,5,3.7,8,4.4v-43.8                            C96.7,136.6,98.4,134.9,100.5,134.9' />                    <path d='M62.3,96.7L62.3,96.7c2.1,0,3.8,1.7,3.8,3.8v24.3c0,5.6,4.5,10.1,10,10.1c5.5,0,10-4.5,10-10.1v-24.3                            c0-2.1,1.7-3.8,3.8-3.8h6.9v-3.2H76.2c-9.7,0-17.6-7.9-17.6-17.5s7.9-17.5,17.6-17.5h20.5V18.5c-3,0.7-5.8,2.2-8,4.4L22.9,88.7                            c-2.2,2.2-3.7,5-4.4,8H62.3z' />                    <path d='M100.5,66.1H76.2c-5.6,0-10.1,4.5-10.1,10c0,5.5,4.5,10,10.1,10h24.3c2.1,0,3.8,1.7,3.8,3.8v6.9h3.1V76.2                            c0-9.7,7.9-17.6,17.5-17.6c9.7,0,17.5,7.9,17.5,17.6v20.5h40.1c-0.7-3-2.2-5.8-4.4-8l-65.8-65.8c-2.2-2.2-5-3.7-8-4.4v43.8                            C104.3,64.4,102.6,66.1,100.5,66.1' />                    <path d='M134.9,100.5V76.2c0-5.6-4.5-10.1-10-10.1c-5.5,0-10,4.5-10,10.1v24.3c0,2.1-1.7,3.8-3.8,3.8h-6.9v3.1h20.5                            c9.7,0,17.6,7.9,17.6,17.5s-7.9,17.5-17.6,17.5h-20.5v40.1c3-0.7,5.8-2.2,8-4.4l65.8-65.8c2.2-2.2,3.7-5,4.4-8h-43.8                            C136.6,104.3,134.9,102.6,134.9,100.5' />                </svg>"},"activo":1}],"check":false,"svg":{"clasehtml":"d_ejeinclusion","datasvg":{"changingThisBreaksApplicationSecurity":" <svg viewBox='0 0 200 200'>\n                    <path d='M100.5,134.9h24.3c5.6,0,10.1-4.5,10.1-10c0-5.5-4.5-10-10.1-10h-24.3c-2.1,0-3.8-1.7-3.8-3.8v-6.9h-3.1v20.5\n                            c0,9.7-7.9,17.6-17.5,17.6c-9.7,0-17.5-7.9-17.5-17.6v-20.5h-40c0.7,3,2.2,5.8,4.4,8l65.8,65.8c2.2,2.2,5,3.7,8,4.4v-43.8\n                            C96.7,136.6,98.4,134.9,100.5,134.9' />\n                    <path d='M62.3,96.7L62.3,96.7c2.1,0,3.8,1.7,3.8,3.8v24.3c0,5.6,4.5,10.1,10,10.1c5.5,0,10-4.5,10-10.1v-24.3\n                            c0-2.1,1.7-3.8,3.8-3.8h6.9v-3.2H76.2c-9.7,0-17.6-7.9-17.6-17.5s7.9-17.5,17.6-17.5h20.5V18.5c-3,0.7-5.8,2.2-8,4.4L22.9,88.7\n                            c-2.2,2.2-3.7,5-4.4,8H62.3z' />\n                    <path d='M100.5,66.1H76.2c-5.6,0-10.1,4.5-10.1,10c0,5.5,4.5,10,10.1,10h24.3c2.1,0,3.8,1.7,3.8,3.8v6.9h3.1V76.2\n                            c0-9.7,7.9-17.6,17.5-17.6c9.7,0,17.5,7.9,17.5,17.6v20.5h40.1c-0.7-3-2.2-5.8-4.4-8l-65.8-65.8c-2.2-2.2-5-3.7-8-4.4v43.8\n                            C104.3,64.4,102.6,66.1,100.5,66.1' />\n                    <path d='M134.9,100.5V76.2c0-5.6-4.5-10.1-10-10.1c-5.5,0-10,4.5-10,10.1v24.3c0,2.1-1.7,3.8-3.8,3.8h-6.9v3.1h20.5\n                            c9.7,0,17.6,7.9,17.6,17.5s-7.9,17.5-17.6,17.5h-20.5v40.1c3-0.7,5.8-2.2,8-4.4l65.8-65.8c2.2-2.2,3.7-5,4.4-8h-43.8\n                            C136.6,104.3,134.9,102.6,134.9,100.5' />\n                </svg>"},"datasvghtml":""}},{"id":22,"id_padre":8,"label":"Pensamiento crítico","activo":1,"detalles":[],"check":false,"svg":{"clasehtml":"d_ejepensamiento","datasvg":{"changingThisBreaksApplicationSecurity":" <svg viewBox='0 0 200 200'>\n                        <path d='M100.5,18.6c-45.2,0-82,36.8-82,81.9c0,3,2.4,5.4,5.4,5.4h24.5c-0.2-1.8-0.3-3.6-0.3-5.4\n                                c0-28.8,23.5-52.3,52.3-52.3c28.8,0,52.3,23.5,52.3,52.3c0,28.8-23.5,52.3-52.3,52.3c-1.8,0-3.6-0.1-5.4-0.3V177\n                                c0,3,2.4,5.4,5.4,5.4c45.2,0,82-36.8,82-82C182.5,55.3,145.7,18.6,100.5,18.6' />\n                        <path\n                            d='M100.4,131.1l-30.5-30.7l30.7-30.5l30.5,30.7L100.4,131.1z M100.5,54.6c-25.4,0-45.9,20.6-45.9,45.9\n                                c0,25.4,20.6,45.9,45.9,45.9c25.4,0,45.9-20.6,45.9-45.9C146.4,75.1,125.9,54.6,100.5,54.6' />\n                    </svg>"},"datasvghtml":""}},{"id":23,"id_padre":8,"label":"Interculturalidad crítica","activo":1,"detalles":[],"check":false,"svg":{"clasehtml":"d_ejeintercult","datasvg":{"changingThisBreaksApplicationSecurity":" <svg viewBox='0 0 200 200'>\n                        <path d='M102.4,76l34.5-34.5H64.1L98.6,76C99.6,77,101.4,77,102.4,76' />\n                        <path d='M98.6,125l-34.5,34.5h72.8L102.4,125C101.4,124,99.6,124,98.6,125' />\n                        <path d='M41.5,64.1v72.8L76,102.4c1-1,1-2.8,0-3.8L41.5,64.1z' />\n                        <path d='M163.2,145.8l-1,0.2l-1.9-0.8l-12.8-12.8c-4,5.9-9.1,11-15.1,15.1l12.8,12.8c0.8,0.8,1,1.9,0.6,2.9\n                                c-0.4,1-1.4,1.7-2.5,1.7H57.6c-1.1,0-2.1-0.7-2.5-1.7c-0.4-1-0.2-2.2,0.6-2.9l39.1-39.1c1.5-1.5,3.5-2.4,5.7-2.4\n                                c2.1,0,4.2,0.8,5.7,2.4l13.3,13.3c6.3-3.5,11.5-8.7,15.1-15.1l-13.2-13.2c-3.1-3.1-3.1-8.2,0-11.4l39.1-39.1c0.8-0.8,1.9-1,2.9-0.6\n                                c1,0.4,1.7,1.4,1.7,2.5v85.7C164.9,144.4,164.2,145.4,163.2,145.8 M40.7,145.2l-1.9,0.8l-1-0.2c-1-0.4-1.7-1.4-1.7-2.5V57.6\n                                c0-1.1,0.7-2.1,1.7-2.5c1-0.4,2.2-0.2,2.9,0.6l12.8,12.8c4-5.9,9.1-11,15.1-15.1L55.8,40.7c-0.8-0.8-1-1.9-0.6-2.9\n                                c0.4-1,1.4-1.7,2.5-1.7h85.7c1.1,0,2.1,0.7,2.5,1.7c0.4,1,0.2,2.2-0.6,2.9l-39.1,39.1c-1.5,1.5-3.5,2.4-5.7,2.4\n                                c-2.1,0-4.2-0.8-5.7-2.4L81.5,66.5C75.2,70,70,75.2,66.5,81.5l13.3,13.3c3.1,3.1,3.1,8.2,0,11.4L40.7,145.2z M100.5,18.5\n                                c-45.3,0-82,36.7-82,82s36.7,82,82,82c45.3,0,82-36.7,82-82S145.8,18.5,100.5,18.5' />\n                        <path\n                            d='M125,102.4l24.9,24.9l0.5,0.3l-0.1,0.1l9.2,9.2V64.1L125,98.6C124,99.6,124,101.4,125,102.4' />\n                    </svg>"},"datasvghtml":""}},{"id":24,"id_padre":8,"label":"Igualdad de género","activo":1,"detalles":[],"check":false,"svg":{"clasehtml":"d_ejeigualdad","datasvg":{"changingThisBreaksApplicationSecurity":"<svg viewBox='0 0 200 200'>\n                        <path d='M122,64.1c-2-2-5.3-2-7.3,0l-50.6,50.6c-2,2-2,5.3,0,7.3c2,2,5.3,2,7.3,0L122,71.5\n                                C124.1,69.4,124.1,66.2,122,64.1' />\n                        <path d='M136.9,79c-2-2-5.3-2-7.3,0L79,129.5c-2,2-2,5.3,0,7.3c2,2,5.3,2,7.3,0l50.6-50.6C138.9,84.3,138.9,81,136.9,79\n                                ' />\n                        <path\n                            d='M75,90.5c-1-3-4.2-4.7-7.2-3.7C65,87.7,62,88.2,59,88.2c-16.1,0-29.2-13.1-29.2-29.2c0-7.8,3-15.1,8.6-20.7\n                                c5.5-5.5,12.8-8.6,20.6-8.6h0c7.8,0,15.1,3,20.6,8.6c5.5,5.5,8.6,12.8,8.6,20.6c0,3-0.5,6-1.4,8.9c-1,3,0.7,6.2,3.7,7.2\n                                c3,1,6.2-0.7,7.2-3.7c1.3-4,1.9-8.1,1.9-12.3c0-10.8-4.2-21-11.9-28.7C80,22.6,69.8,18.4,59,18.4h0c-10.8,0-21,4.2-28.7,11.9\n                                C22.6,37.9,18.3,48.1,18.3,59c0,22.4,18.2,40.6,40.6,40.6c4.2,0,8.3-0.6,12.3-1.9C74.3,96.7,75.9,93.5,75,90.5' />\n                        <path d='M170.8,113.3c-7.7-7.7-17.9-11.9-28.7-11.9c-4.9,0-9.7,0.9-14.2,2.6c-2.9,1.1-4.4,4.4-3.3,7.3\n                                c1.1,3,4.4,4.5,7.3,3.3c3.3-1.2,6.7-1.8,10.2-1.8c7.8,0,15.1,3,20.6,8.5c5.5,5.5,8.6,12.9,8.6,20.7c0,7.8-3,15.1-8.6,20.7\n                                c-5.5,5.5-12.8,8.6-20.6,8.6c-16.1,0-29.2-13.1-29.2-29.2c0-2.5,0.3-5,1-7.4c0.8-3-1-6.2-4.1-7c-3-0.8-6.2,1-7,4.1\n                                c-0.9,3.4-1.3,6.8-1.3,10.3c0,22.4,18.2,40.6,40.6,40.6c10.8,0,21-4.2,28.7-11.9c7.7-7.7,11.9-17.9,11.9-28.7\n                                C182.7,131.2,178.4,121,170.8,113.3' />\n                        <path d='M47.1,47.1c-3.7,3.7-3.7,9.8,0,13.5c3.7,3.7,9.8,3.7,13.5,0c3.7-3.7,3.7-9.8,0-13.5\n                                C56.9,43.4,50.8,43.4,47.1,47.1' />\n                    </svg>"},"datasvghtml":""}},{"id":25,"id_padre":8,"label":"Vida saludable","activo":1,"detalles":[],"check":false,"svg":{"clasehtml":"d_ejevida","datasvg":{"changingThisBreaksApplicationSecurity":"<svg viewBox='0 0 200 200'>\n                        <path\n                            d='M56.7,110.3c-1,3.7-1.5,7.5-1.5,11.4c0,19.4,12.2,35.9,29.4,42.4C69.1,150.3,59.1,131.1,56.7,110.3' />\n                        <path\n                            d='M100.5,35.1c-22.6,14-36.6,38.9-36.6,65.6c0,25.1,12.4,48.7,32.7,63.1V93.4c0-2.1,1.7-3.9,3.9-3.9\n                                c2.1,0,3.9,1.7,3.9,3.9v70.4c20.4-14.4,32.7-37.9,32.7-63.1C137.1,74.1,123.1,49.1,100.5,35.1' />\n                        <path d='M100.5,174.8L100.5,174.8L100.5,174.8c-0.9,0-1.8,0-2.7-0.1l-0.5,0c-39.7-1.7-71.4-34.5-71.4-74.6\n                                c0-15.5,4.7-30.4,13.7-43.1c1.2-1.8,3.6-2.2,5.4-0.9c1.8,1.2,2.2,3.7,0.9,5.4c-8,11.3-12.3,24.7-12.3,38.6c0,10,2.2,19.5,6.2,28.1\n                                c-1.4-5.2-2.2-10.6-2.2-16.3c0-13.1,4-25.6,11.5-36.3c1.2-1.8,3.7-2.2,5.4-0.9c1.7,1.2,2.2,3.7,0.9,5.4\n                                c-6.6,9.3-10.1,20.3-10.1,31.8c0,5.7,0.9,11.3,2.5,16.5c-0.3-2.2-0.4-4.4-0.4-6.6c0-10.7,3.2-20.9,9.1-29.7\n                                c2.8-26.8,18.3-51.1,42-64.8c1.2-0.7,2.7-0.7,3.9,0l0.2,0.1c23.5,13.7,39,37.9,41.8,64.7c6,8.8,9.1,19,9.1,29.7\n                                c0,2.2-0.2,4.5-0.4,6.6c1.6-5.2,2.5-10.7,2.5-16.5c0-11.5-3.5-22.5-10.1-31.8c-1.2-1.7-0.8-4.2,0.9-5.4c1.8-1.2,4.2-0.8,5.4,0.9\n                                c7.5,10.6,11.5,23.2,11.5,36.3c0,5.6-0.8,11.1-2.2,16.3c4-8.5,6.2-18.1,6.2-28.1c0-13.9-4.2-27.3-12.3-38.6\n                                c-1.2-1.7-0.8-4.2,0.9-5.4c1.7-1.2,4.2-0.8,5.4,0.9c8.9,12.6,13.7,27.5,13.7,43.1C175.2,141.3,141.7,174.8,100.5,174.8 M167.8,52.6\n                                c-3.7-5.2-11-6.5-16.2-2.8c-5.2,3.7-6.5,11-2.8,16.2l0.2,0.3c-1,0-2,0.1-3,0.3c-7.6-18.9-21.3-35.2-39.4-45.8l-0.3-0.2\n                                c-3.6-2.1-8-2.1-11.6,0c-18.3,10.6-32.1,27-39.7,46c-1-0.2-2-0.3-3-0.3l0.2-0.3c3.7-5.2,2.5-12.5-2.8-16.2\n                                c-5.2-3.7-12.5-2.5-16.2,2.8c-9.9,14-15.1,30.4-15.1,47.5c0,44.2,35,80.4,78.8,82.3c1.2,0.1,2.4,0.1,3.6,0.1h0\n                                c45.4,0,82.4-37,82.4-82.4C182.9,83,177.7,66.5,167.8,52.6' />\n                        <path\n                            d='M116.4,164.1c17.2-6.4,29.4-23,29.4-42.4c0-3.9-0.5-7.7-1.5-11.4C141.9,131.1,131.9,150.3,116.4,164.1' />\n                    </svg>"},"datasvghtml":""}},{"id":26,"id_padre":8,"label":"Apropiación de las culturas a través de la lectura y la escritura","activo":1,"detalles":[],"check":false,"svg":{"clasehtml":"d_ejeapropiacion","datasvg":{"changingThisBreaksApplicationSecurity":"<svg viewBox='0 0 200 200'>\n                        <path d='M121.4,117.2l43.8-43.8c-36.5-36.5-95.3-37.1-132.5-1.8l46.5,45.9c5.9-4.6,13.3-7.4,21.3-7.4\n                                C108.4,110,115.6,112.7,121.4,117.2' />\n                        <path d='M183.7,146.5l-1.7-17.2l-77.4,15.4c-1.1-0.8-2.5-1.2-3.9-1.2c-1.5,0-2.8,0.5-3.9,1.2l-77.4-15.3l-2.1,17.2\n                                l77.5,15.4c1.2,1.8,3.3,2.9,5.6,2.9c2.3,0,4.3-1.1,5.6-2.9L183.7,146.5z' />\n                        <path\n                            d='M75.4,121L39.9,85.9c-9.5,10.6-16.3,23.8-19.2,38.3l47.2,9.4C69.5,128.9,72,124.6,75.4,121' />\n                        <path\n                            d='M160.6,85.3l-35.3,35.3c3.5,3.7,6.2,8.1,7.9,13l47.2-9.4C177.4,109.5,170.4,96.1,160.6,85.3' />\n                        <path d='M105.4,139.2l22.7-4.5c-4.1-11.3-14.8-19.4-27.6-19.4c-12.7,0-23.5,8.1-27.5,19.4l23,4.6\n                                C98.9,137.9,102.4,137.9,105.4,139.2' />\n                    </svg>"},"datasvghtml":""}},{"id":27,"id_padre":8,"label":"Artes y experiencias estéticas","activo":1,"detalles":[],"check":false,"svg":{"clasehtml":"d_ejeartes","datasvg":{"changingThisBreaksApplicationSecurity":"<svg viewBox='0 0 200 200'>\n                        <path\n                            d='M76,161.3c-0.7,0.3-1.3-0.4-1.5,0.4c1.8,0,3.5,1.7,5.9,1.7C79.8,161.8,77.1,162.3,76,161.3 M72.6,159.6\n                                l-1.3-0.4c-4-3.2-8.5-4.6-11.8-8.4c-3.5-0.9-4.3-5.4-8-5.5c1.5,1.9,2.7,4.1,4.6,5.5l1.7,0.8c1,0.7,1.7,1.9,2.7,2.7l1.9,1.1\n                                c3.3,2.1,7.5,4.9,11.2,5.7l0.2-0.2L72.6,159.6 M61.2,140.8c0.8,1,3,1.7,2.7,3.6c1.5-0.4,1-1.3,1.9-1.7c0.4,0.8,1.9,1.3,3,1.3\n                                c1.4,0,2.7,0.7,3.3,2c0.3,0.8,0.7,1.3,1.3,1.2c1.7,1,3,2,3.9,3.8c0.9,0.1,1,0.1,1.9,0.4l0.2,1.1c2.1,0.3,2.7-1.4,4.6-0.8\n                                c2.5-2.5,6-1.6,9.4-1.6c0.9,0,1.7-0.5,2.5-1.1c0.5-0.4,1.2-0.3,2-0.7c0.4,0.6-0.1,1,0.2,1.7l1.1,0.8c1.3-0.5,2.8-1.6,1.5-2.1\n                                c1.6-0.5,2.5-1,4-1.1c0.3,0.8,0.9,0.6,0.6,1.7c2.7-0.1,4.6-0.3,6.6-0.8l0.6,1.3c1.3,0.5,1.6-1.1,3.2-0.8l-0.2,1.7\n                                c1.1,0.8,1.9-0.2,3.4,0l1.3-0.8c4.2-0.2,6.2-2.7,8.9-4.2c1.1-0.6,2.1-1,2.8-1.7c5.8-5,10.4-11.9,15.8-17.3c0.9-2.1,2.6-3.3,4-4.9\n                                l1.3,0.8c1.5-0.9,0.2-4.9,2.5-4.6c1.9,0.2,1.1,3.5,1.3,5.5c0.1,1.2,0.8,2.1,0.8,3.2c0,1.5-0.8,2.7,0.2,3.4c1.8-1,2.3-3.5,2.7-5.3\n                                c1-5,0.7-11,1.1-16.1l0.4-1.5c0-1-0.6-2-0.6-3c0-3.5,3.6-6.6,1.7-10.3c3.4-4.4,1.3-11.2,0.2-17.1c-0.8-4.3-2.7-8.3-3.4-11.8\n                                l-1.3-1.1c-2.3-8.6-6.8-14.8-12.3-20.1c-1.2,0.2-1.7,0.1-2.7,0.6l-0.4-1.1c-0.9,0.1-1.7,0.4-1.7-0.8c1.1,0.1,1.8,0.2,3,0.4l-0.5-0.7\n                                l-0.8-1.8c-8.1-8.2-20.4-14-33.5-15.4c-5.8-1.2-11.8-0.9-17.5-0.2c-2.1,0.3-4,1.6-6.2,1.6l-1.6,0.2c-4.8,1.9-9.9,3.4-13.7,6.3h-0.8\n                                c-2.4,2-5.6,3.2-7.6,5.5c-4.4,2.7-7.5,6.7-11.4,9.9v0.9c-2.3,1-2.4,3.2-3.6,5.1l0.8,0.9c-2.3,2.4-2,8.2-5.9,8.4c2,2.3-0.1,5.3-1.7,7\n                                c0.7,0.8-0.3,1.6-0.6,2.1c0.2,1.2-0.3,2-0.3,2.9c0,0.7-0.2,1.4-0.6,2c-1.2,1.8-2.9,3-2.3,5.4L35.7,83l-0.8,0.8\n                                c-0.5,3.6-0.3,8.2-0.2,12.7c0,2.1,0.6,4,0.8,5.9c0.1,1.8-0.7,3.9,0.9,4.9c0.5,0-0.2-1.2,0.6-0.9l0.8,1.1c0.1,0.8-0.9,0.6-0.6,1.7\n                                c1.6,0.2,3.1-2.9,3.2-3.4l0.2-1.1c0.6-1.3,4-5.7,3.8-5.9c1-2.6-2.2-7.3,0.4-8.7c0-4.2-1.1-6.9-0.2-11.6c-0.1-0.6-1-0.4-0.9-1.1\n                                c0.2-0.6,0.9-0.6,0.9-1.3c1.1-2.9,0.9-5.5,1.3-8.4c0.4-3,3.1-5,2.7-8.4c0.7-0.5,1.2-1.3,1.5-2.3c0.3-1,1.2-1.9,2.2-2.1\n                                c0.8-0.2,1.5-0.7,1.7-1.3c-0.1-0.9-0.9-1.1-0.9-2.1c1.8-3.4,5.2-5.2,6.8-8.7c1.2,0.2,1.2-0.9,1.7-1.3c8.8-6.6,21.6-11.1,35.1-10.3\n                                l0.8,0.9c1.2,0.2,2.3,0.6,3.6,0.8c1.6,1.7,4.8,1.8,7.2,2.8c3.2,1.4,6.8,3.3,10.1,4.6c4.6,1.7,9.7,3.4,12.9,6.3\n                                c3.7,3.3,4.7,8.2,6.8,12.7c0.7,1.5,1.6,2.9,2.3,4.4l0.4,1.4c0.6,2.4,5.5,13.7,7.3,14.8c0.4,1,0.8,2.2,0.2,3.2\n                                c-2-1.1,0.8,9.9,0.8,12.7c0,1.2-1.2,2.6-1.5,4.2c-0.2,1-0.3,2.1-0.4,3c-0.1,1.2-0.5,2.4-0.6,3.4c-0.2,2.3,1.1,4.6,1,6.8\n                                c-0.3,5-3.6,8.1-5.2,11.5l-1.1,1.4c-3.1,2.5-5.1,6.1-8.8,8l-0.8,1.3c-5.1,5-17.7,7.2-18.8,7.6c-1.6,0.6-4.7,0.4-6.3,0.6\n                                c-6.5,0.8-14.5-0.5-20.3-2.1c-1.6-0.4-3.3-1.5-4.4-1.9c-2.5-0.9-4.5-0.3-5.3-2.5l-1.3,0.2c-2-1.5-4.3-2.7-6.4-3.7l-1.6-1.4\n                                c-2.3-3.4-6.2-5-8.2-8.7c-4.5-2.5-6-7.9-9.5-11.4c-1,1,1.1,3.5-0.4,4.7c0.7,1.5,1.3,4.1,1.2,6.4c0,0.8,0.2,1.6,0.7,2.2\n                                c0.9,1,1,2.6-0.4,3.2c-0.1,1.5,1.6,3.4,1.3,5.1c1.1,0.3,1.6-0.1,1.9-0.9c0.8,1,0.8,2.8,1.3,4c1,0.2,0.8-0.8,1.7-0.8l1.7,1.1\n                                c-0.4,1.4,0.9,1.1,1.3,1.7 M40.6,125.6c0.2-1-0.7-2-1.1-3l-0.8,0.2c0.9,1.8,0.8,4.5,2.1,5.9c0.7,3.8,3.5,6.9,5.4,10.3l0.9,1.1\n                                c1.1,1,1.9,2.5,3.2,3.3c-0.2-1.6-1.6-1.9-1.7-3.6C44.9,136.2,43.5,130.1,40.6,125.6 M38.2,115.5l0.6-0.2c0.1-1.6-0.7-3.7,0.2-4\n                                c0-1.1-0.8-1.6-1.7-1.3c-0.2-0.9-1.1-0.9-0.8-2.3h-0.6c0,4.6,0.9,10.2,2.7,14.8C40.9,121.7,38.3,117.6,38.2,115.5 M47.1,36.1\n                                c3.3,2.1,7.1-0.4,8.1-3.3c0.3-0.7,0.2-1.5,0-2.3c-1.5-5.5-9.4-4.5-10.1,0.8C45.1,32.5,45.6,35.2,47.1,36.1' />\n                        <path\n                            d='M90.9,30.7c-4.7,2.6,0.4,12.7,6.9,3.1C101.5,27.6,92.9,29.2,90.9,30.7 M84.3,69.5c-1.3-2.9,0.1-7.1-1.4-6.2\n                                C81.9,62.7,73.7,67.5,84.3,69.5 M143.8,58.3c3.9,0,7.5-0.8,5-4.1C147.9,54.2,143.6,57.9,143.8,58.3 M103.3,108.5\n                                c0,0.5,0.6,4.9,1.4,5.4c0.3-0.8-1.2-5.6-0.4-5.8c2,1.3,2.6,3.6,3.3,5.8c6.3,7.3,5.4,11.7,9.9,20.1l3.7,4.2l0.6,0.4\n                                c-0.2,1.3,0.7-0.2,1.2-0.1c3.5,2.9,4.3,7.6,6.1,11.8c1.9,4.5,6,9,8.7,13.4c2,3.3,4.3,6.3,6.2,9.5c0.8,1.4,0.9,4.1,3.5,2.9\n                                c0.7-2.1-1.4-3.2-2.4-4.5c-5.2-6.7-8-15.1-13.6-21.4c-2.5-4-4.1-8.5-6.5-12.7c-1.4-2.4-3.3-4.5-4.6-6.9c-2-3.7-3.4-7.6-5.6-10.8\n                                c-2.1-3-7.8-9-4.2-12.3c4.8,2.1,12.6,2.5,15.9,6.8c0-1.4-2.3-3.3-1.5-4.9c-1.5-1.6-4.4-2.1-5.4-4.1c1.1-1.1,1-3.8,2.2-4.5\n                                c3.7,3.2,10,6.2,15.7,5.9c-2.6-2.2-9.6-2.1-12.1-5c0.3-0.6,0.9-0.8,0.9-1.9c-2.1-2.6-5.2-4.4-6.2-7.7l6.5,2.9\n                                c0.4-0.9-3.9-3.7-3.7-4.4c2.7,0,3.6-1.3,6.7-1.7c3-0.4,7,0.9,8.7-2c-2.4-2.4-6.3,0.7-9.9,0.6c-0.8,0-1.4-0.6-2.2-0.7\n                                c-2.1-0.3-5,0.8-6.2-1.1c2.2-2,4.1-4.9,6.9-6.3c1-0.5,2.9-0.4,2.9-1.8c-3.8,1.5-8,2.4-11.5,4.4c-5.7-2.2-2.8-6.8,0-9.8\n                                c1-1.2,1.7-2.5,2.3-3.1c1-1,2.8-1.5,3.9-2.5c1.9-1.7,3.3-3.7,4.8-4.4c0.9-0.4,2.1-0.2,3-0.6c1.2-0.5,2.3-2.1,3.7-3.1\n                                c1.6-1.2,3.7-1.9,4.8-2.9c0.9-0.9,1.1-2.2,2-3.1c2.8-3,6.9-4.9,8.3-8.1c-0.2-1-1.1-1.5-2.6-1.6c-2.8,1.5-4.5,4.7-7.4,6.2\n                                c-0.9,0.5-2.2,0.3-3,0.9c-1.3,1-1.4,2.6-2.4,3.9c-1.2,1.7-3.4,2.5-5,4c-0.9,0.8-1.2,2-1.9,2.8c-4.4,4.6-10.9,7.1-14.7,11.3\n                                c-1.7-0.2-3.4,1.4-5.2,0c0.6-1.1,0.7-2.8,1.7-3.2c-3.3-1-5.1-3.2-5.6-6.2c1.5-2.7,4.4-6.8,4-10c-2.7-0.8-2.8,2.3-3.6,4\n                                c-1.9,4.1-4.9,9.1-9.1,7.7c-0.7,0.5,0.1,1.4-0.4,2.5c-1.5,1-4.2-0.5-5.2-1.5c-3.6-3.3-1-11.7-6.3-11.8c-4.8,5.8,5.3,10.2,2.2,17.2\n                                c-2,1.5-5.5,3-6.5-0.6c-1.6-0.3-1.1,2.1-2.6,1.9c-1.1,0.2-0.4-0.9-1.3-0.8l-0.7,0.7c-3.9,0-9.3-3.5-10.2,0.3c1.9,1.4,6.5,0.8,5,4.6\n                                c-3.1,1.1-5.4-1.7-8.6-2.1c-1.3-0.8-4.7-3.9-6.1-1.6c3.3,4,12.5,3.8,14,9.1c-2,1.5-7.1,2.1-10.2,2c-2.6-0.1-10-3.1-12.5,0.2\n                                c-2.4,3.3,3.1,6.4,5.8,6.5c4.4,0.2,7.7-5.7,12.5-5.3c1.2,0.1,3.6,0.7,5,1.4c1.3,0.8,4.6,4.1,5.6,6.2c1.2,2.4,2,4.2,1.4,7.2\n                                c-3.5,4.6-5.9,9.6-10.8,12.3c-1.8,1-4.8,0.9-4.7,3.8c1.8,1.2,3.5-0.5,4.4-1.8c2.8-1.3,5.4-2.8,7.8-4.7c1.1-0.1,2.3,0,3.7,0.4\n                                c0.9,1.2,1.8,2.5,3.8,3c0.4,0.5-0.5,1.1-0.4,2.2c0.4,0.7,1.6,0.8,1.7,1.7c-0.1,4.5-1.6,7.8-2.4,12c-0.7,3.9-3.7,5.5-4.7,8.7\n                                c-1.1,3.5-2.2,4.9-2.2,7.7c0.9,1.3,2.3,1.2,3.6,0.6c1.7-4.3,5.1-5.6,5.2-10.1c0-1-0.7-2.1-0.6-3.3c0.4-3.7,3.3-7.1,4.2-11.1\n                                c2.2-0.3,3-2.5,4.2-4.2c0.9,0.3,0.8,1,1.9,0.6c0.6-0.4,0.6-1.7,1.5-1.8c0.5,0.6,2.4,0.2,1.8,1.5c1,0.5,0.9-1.3,1.5-0.3\n                                c2.1,2.7-2.2,7,0.1,9.3c3.7-0.8,0.2-7.8,3.5-8.6c0.5,1.1-0.3,3.2,1.4,3.4c0.7-2.1-1.2-3.8-1-6c0.1-1.3,1.2-2.5,1.5-3.8\n                                C102.2,111.2,101.6,108.4,103.3,108.5 M66.4,117c2.4,3.2,8.4-1.6,5.5-3.3C68.7,113.4,66.5,116.3,66.4,117 M111.4,115.1\n                                c1,0.1,12.4,0,4.5-2.8C115,112.4,112.1,112,111.4,115.1 M131.8,117.7c1.9-4.6-2.5-4-3.5-3.4C126,115.2,129,120.5,131.8,117.7\n                                M123.5,78.2c1.2-0.9,3-1.1,4.4-1.8c1-0.1,0.9,0.3,2,0.1c0.3-1.7,6.3-4.6,5.2-5.9C132.1,72,125,75.6,123.5,78.2 M134.6,66.2\n                                c5.2,2.5,13.3-3.3,5.1-4.2C138.7,63,135.3,64.9,134.6,66.2 M64.1,50.8c-0.5,2.8,2.2,5.1,5.6,4.2C77.5,51.8,65.3,44.2,64.1,50.8\n                                M63.7,36.6c-4.6,2.5-1.1,4.6,0.3,4.6C72.4,41.1,66.6,34.6,63.7,36.6 M118.1,38.3c-17.3,0.1,14.5,10,4.3,0.3L118.1,38.3z' />\n                        </svg>"},"datasvghtml":""}}]}